[
  {
    "ContainingType": "RealEstateAPI.Controllers.PropertyController",
    "Method": "Get",
    "RelativePath": "api/Property",
    "HttpMethod": "GET",
    "IsController": true,
    "Order": 0,
    "Parameters": [],
    "ReturnTypes": [
      {
        "Type": "System.Collections.Generic.List\u00601[[RealEstateAPI.Models.Property, RealEstateAPI, Version=1.0.0.0, Culture=neutral, PublicKeyToken=null]]",
        "MediaTypes": [
          "text/plain",
          "application/json",
          "text/json"
        ],
        "StatusCode": 200
      }
    ]
  },
  {
    "ContainingType": "RealEstateAPI.Controllers.PropertyController",
    "Method": "Post",
    "RelativePath": "api/Property",
    "HttpMethod": "POST",
    "IsController": true,
    "Order": 0,
    "Parameters": [
      {
        "Name": "newProperty",
        "Type": "RealEstateAPI.Models.Property",
        "IsRequired": true
      }
    ],
    "ReturnTypes": []
  },
  {
    "ContainingType": "RealEstateAPI.Controllers.PropertyController",
    "Method": "Get",
    "RelativePath": "api/Property/{id}",
    "HttpMethod": "GET",
    "IsController": true,
    "Order": 0,
    "Parameters": [
      {
        "Name": "id",
        "Type": "System.String",
        "IsRequired": true
      }
    ],
    "ReturnTypes": []
  },
  {
    "ContainingType": "RealEstateAPI.Controllers.PropertyController",
    "Method": "Put",
    "RelativePath": "api/Property/{id}",
    "HttpMethod": "PUT",
    "IsController": true,
    "Order": 0,
    "Parameters": [
      {
        "Name": "id",
        "Type": "System.String",
        "IsRequired": true
      },
      {
        "Name": "updatedProperty",
        "Type": "RealEstateAPI.Models.Property",
        "IsRequired": true
      }
    ],
    "ReturnTypes": []
  },
  {
    "ContainingType": "RealEstateAPI.Controllers.PropertyController",
    "Method": "Delete",
    "RelativePath": "api/Property/{id}",
    "HttpMethod": "DELETE",
    "IsController": true,
    "Order": 0,
    "Parameters": [
      {
        "Name": "id",
        "Type": "System.String",
        "IsRequired": true
      }
    ],
    "ReturnTypes": []
  },
  {
    "ContainingType": "RealEstateAPI.Controllers.PropertyController",
    "Method": "Get",
    "RelativePath": "api/Property/filtered",
    "HttpMethod": "GET",
    "IsController": true,
    "Order": 0,
    "Parameters": [
      {
        "Name": "name",
        "Type": "System.String",
        "IsRequired": false
      },
      {
        "Name": "address",
        "Type": "System.String",
        "IsRequired": false
      },
      {
        "Name": "minPrice",
        "Type": "System.Nullable\u00601[[System.Decimal, System.Private.CoreLib, Version=8.0.0.0, Culture=neutral, PublicKeyToken=7cec85d7bea7798e]]",
        "IsRequired": false
      },
      {
        "Name": "maxPrice",
        "Type": "System.Nullable\u00601[[System.Decimal, System.Private.CoreLib, Version=8.0.0.0, Culture=neutral, PublicKeyToken=7cec85d7bea7798e]]",
        "IsRequired": false
      }
    ],
    "ReturnTypes": []
  },
  {
    "ContainingType": "RealEstateAPI.Controllers.WeatherForecastController",
    "Method": "Get",
    "RelativePath": "WeatherForecast",
    "HttpMethod": "GET",
    "IsController": true,
    "Order": 0,
    "Parameters": [],
    "ReturnTypes": [
      {
        "Type": "System.Collections.Generic.IEnumerable\u00601[[RealEstateAPI.WeatherForecast, RealEstateAPI, Version=1.0.0.0, Culture=neutral, PublicKeyToken=null]]",
        "MediaTypes": [
          "text/plain",
          "application/json",
          "text/json"
        ],
        "StatusCode": 200
      }
    ],
    "EndpointName": "GetWeatherForecast"
  }
]